nauti/__init__.py
nauti/collection.py
nauti/config.py
nauti/config_models.py
nauti/consts.py
nauti/diff.py
nauti/entrypoints.py
nauti/filtering.py
nauti/igather.py
nauti/log.py
nauti/mappings.py
nauti/normalize_hostname.py
nauti/slugify.py
nauti/source.py
nauti/collections/__init__.py
nauti/collections/devices.py
nauti/collections/interfaces.py
nauti/collections/ipaddrs.py
nauti/collections/portchans.py
nauti/collections/sites.py
nauti-0.1.0.dist-info/LICENSE
nauti-0.1.0.dist-info/METADATA
nauti-0.1.0.dist-info/WHEEL
nauti-0.1.0.dist-info/entry_points.txt
nauti-0.1.0.dist-info/top_level.txt
nauti-0.1.0.dist-info/RECORD
