Metadata-Version: 2.1
Name: nauti
Version: 0.1.0
Summary: Network Automation Tools Integrator
Home-page: UNKNOWN
Author: Jeremy Schulman
License: UNKNOWN
Platform: UNKNOWN
Classifier: Development Status :: 3 - Alpha
Classifier: Intended Audience :: Developers
Classifier: Programming Language :: Python :: 3.8
Classifier: Topic :: Software Development :: Libraries :: Python Modules
Classifier: Topic :: System :: Networking
Requires-Dist: click
Requires-Dist: httpx
Requires-Dist: pydantic
Requires-Dist: pydantic-env
Requires-Dist: toml
Requires-Dist: uvloop
Requires-Dist: bidict
